setup.cfg
setup.py
limoncello/__init__.py
limoncello.egg-info/PKG-INFO
limoncello.egg-info/SOURCES.txt
limoncello.egg-info/dependency_links.txt
limoncello.egg-info/entry_points.txt
limoncello.egg-info/top_level.txt
limoncello.egg-info/zip-safe
limoncello/tests/__init__.py
limoncello/tests/model.py
limoncello/tests/test_utils.py