Metadata-Version: 1.0
Name: limoncello
Version: 0.1dev
Summary: SQLAlchemy inspection functions
Home-page: UNKNOWN
Author: Michael Brickenstein, Alberto Valverde
Author-email: brickenstein@mfo.de
License: MIT
Keywords: SQLAlchemy,inspection
Platform: UNKNOWN
